pyJay/__init__.py
pyJay/pyJay.py
pyJay-1.0.5.dist-info/METADATA
pyJay-1.0.5.dist-info/WHEEL
pyJay-1.0.5.dist-info/top_level.txt
pyJay-1.0.5.dist-info/RECORD
