Metadata-Version: 2.1
Name: pyJay
Version: 1.0.5
Summary: Develop games easier
Author: Connor Layson
Author-email: <clayson2573@gmail.com>
Keywords: python,pygame,game
Classifier: Development Status :: 5 - Production/Stable
Classifier: Intended Audience :: Developers
Classifier: Programming Language :: Python :: 3
Classifier: Operating System :: Unix
Classifier: Operating System :: MacOS :: MacOS X
Classifier: Operating System :: Microsoft :: Windows
Requires-Dist: pygame
